CHANGES.md
LICENSE.md
MANIFEST.in
README.md
VERSION
pyproject.toml
requirements-ci.txt
requirements-docs.txt
requirements.txt
setup.cfg
setup.py
bin/radical-bridge
bin/radical-stack
bin/radical-stack-clone
bin/radical-utils-env.sh
bin/radical-utils-fix-headers.pl
bin/radical-utils-pwatch
bin/radical-utils-pylint.sh
bin/radical-utils-scheduler.json
bin/radical-utils-scheduler.py
bin/radical-utils-version
bin/ru.json.sh
examples/app_config.py
examples/benchmark_example.py
examples/configurable.py
examples/debug_helper.py
examples/demunch_timing.py
examples/stack_traces.py
examples/tracer.py
examples/watch_condition.py
examples/zmq_client.py
examples/zmq_registry.py
examples/zmq_server.py
examples/zmq/README.md
examples/zmq/protocols.md
examples/zmq/pubsub/pub.py
examples/zmq/pubsub/pubsub.py
examples/zmq/pubsub/ru_zmq_pubsub.py
examples/zmq/pubsub/sub.py
examples/zmq/queue/get.py
examples/zmq/queue/put.py
examples/zmq/queue/queue.py
examples/zmq/queue/ru_zmq_queue.py
src/radical.utils.egg-info/PKG-INFO
src/radical.utils.egg-info/SOURCES.txt
src/radical.utils.egg-info/dependency_links.txt
src/radical.utils.egg-info/not-zip-safe
src/radical.utils.egg-info/requires.txt
src/radical.utils.egg-info/top_level.txt
src/radical/utils/VERSION
src/radical/utils/__init__.py
src/radical/utils/algorithms.py
src/radical/utils/config.py
src/radical/utils/constants.py
src/radical/utils/daemon.py
src/radical/utils/debug.py
src/radical/utils/dict_mixin.py
src/radical/utils/env.py
src/radical/utils/futures.py
src/radical/utils/get_version.py
src/radical/utils/heartbeat.py
src/radical/utils/host.py
src/radical/utils/ids.py
src/radical/utils/json_io.py
src/radical/utils/lease_manager.py
src/radical/utils/lockable.py
src/radical/utils/lockfile.py
src/radical/utils/logger.py
src/radical/utils/misc.py
src/radical/utils/modules.py
src/radical/utils/object_cache.py
src/radical/utils/plugin_manager.py
src/radical/utils/poll.py
src/radical/utils/profile.py
src/radical/utils/registry.py
src/radical/utils/reporter.py
src/radical/utils/ru_regex.py
src/radical/utils/serialize.py
src/radical/utils/shell.py
src/radical/utils/signatures.py
src/radical/utils/singleton.py
src/radical/utils/stack.py
src/radical/utils/testing.py
