Metadata-Version: 2.4
Name: radical.utils
Version: 1.103.0
Summary: RADICAL-Cybertools utility library
Home-page: http://radical-cybertools.github.io/radical.utils/
Author: RADICAL Group at Rutgers University
Author-email: radical@rutgers.edu
Maintainer: The RADICAL Group
Maintainer-email: radical@rutgers.edu
License: MIT
Project-URL: Documentation, https://radicalutils.readthedocs.io/en/latest/
Project-URL: Source, https://github.com/radical-cybertools/radical.utils/
Project-URL: Issues, https://github.com/radical-cybertools/radical.utils/issues
Keywords: radical,cybertools,utilities
Classifier: Development Status :: 5 - Production/Stable
Classifier: Intended Audience :: Developers
Classifier: Environment :: Console
Classifier: License :: OSI Approved :: MIT License
Classifier: Programming Language :: Python
Classifier: Programming Language :: Python :: 3
Classifier: Programming Language :: Python :: 3.8
Classifier: Topic :: Utilities
Classifier: Topic :: System :: Distributed Computing
Classifier: Topic :: Scientific/Engineering
Classifier: Operating System :: POSIX
Classifier: Operating System :: Unix
Requires-Python: >=3.8
License-File: LICENSE.md
Requires-Dist: colorama
Requires-Dist: msgpack
Requires-Dist: netifaces
Requires-Dist: ntplib
Requires-Dist: pyzmq
Requires-Dist: regex
Requires-Dist: setproctitle
Requires-Dist: rc.process
Dynamic: author
Dynamic: author-email
Dynamic: classifier
Dynamic: description
Dynamic: description-content-type
Dynamic: home-page
Dynamic: keywords
Dynamic: license
Dynamic: license-file
Dynamic: maintainer
Dynamic: maintainer-email
Dynamic: project-url
Dynamic: requires-dist
Dynamic: requires-python
Dynamic: summary
